vladiate/__init__.py
vladiate/exceptions.py
vladiate/exits.py
vladiate/inputs.py
vladiate/logs.py
vladiate/main.py
vladiate/validators.py
vladiate/vlad.py
vladiate/examples/__init__.py
vladiate/examples/vladfile.py
vladiate-0.0.26.dist-info/LICENSE
vladiate-0.0.26.dist-info/METADATA
vladiate-0.0.26.dist-info/WHEEL
vladiate-0.0.26.dist-info/entry_points.txt
vladiate-0.0.26.dist-info/top_level.txt
vladiate-0.0.26.dist-info/RECORD
