Metadata-Version: 2.1
Name: vladiate
Version: 0.0.26
Summary: Vladiate is a strict validation tool for CSV files
Home-page: http://github.com/di/vladiate
Author: Dustin Ingram
Author-email: github@dustingram.com
License: MIT
Keywords: validate CSV vampires
Classifier: Development Status :: 4 - Beta
Classifier: Environment :: Console
Classifier: Natural Language :: English
Classifier: License :: OSI Approved :: MIT License
Classifier: Operating System :: OS Independent
Classifier: Programming Language :: Python
Classifier: Programming Language :: Python :: 3
Classifier: Programming Language :: Python :: 3.7
Classifier: Programming Language :: Python :: 3.8
Classifier: Programming Language :: Python :: 3.9
Classifier: Programming Language :: Python :: 3.10
Classifier: Programming Language :: Python :: 3.11
Classifier: Intended Audience :: Developers
License-File: LICENSE
Provides-Extra: s3
Requires-Dist: boto ; extra == 's3'
